{"queryCost":24,"latitude":47.6062,"longitude":-122.3321,"resolvedAddress":"47.6062, -122.3321","address":"47.6062, -122.3321","timezone":"America/Los_Angeles","tzoffset":-8.0,"days":[{"datetime":"2022-03-10","datetimeEpoch":1646899200,"tempmax":8.2,"tempmin":-1.9,"temp":4.0,"feelslikemax":7.9,"feelslikemin":-5.3,"feelslike":3.1,"dew":-5.7,"humidity":52.9,"precip":0.0,"precipprob":0.0,"precipcover":0.0,"preciptype":null,"snow":0.0,"snowdepth":0.0,"windgust":15.1,"windspeed":10.5,"winddir":161.7,"pressure":1028.3,"cloudcover":46.9,"visibility":15.8,"solarradiation":136.5,"solarenergy":11.9,"uvindex":6.0,"severerisk":10.0,"sunrise":"06:31:57","sunriseEpoch":1646922717,"sunset":"18:07:55","sunsetEpoch":1646964475,"moonphase":0.25,"conditions":"type_42","description":"Variablecloud.","icon":"partly-cloudy-day","stations":["72793024233","KSEA","KBFI","72793524234","72793494248","F0821","KRNT"],"source":"obs","hours":[{"datetime":"00:00:00","datetimeEpoch":1646899200,"temp":1.2,"feelslike":1.2,"humidity":64.56,"dew":-4.7,"precip":0.0,"precipprob":0.0,"snow":0.0,"snowdepth":0.0,"preciptype":null,"windgust":4.7,"windspeed":2.8,"winddir":339.0,"pressure":1027.9,"visibility":16.0,"cloudcover":0.0,"solarradiation":0.0,"solarenergy":null,"uvindex":0.0,"severerisk":10.0,"conditions":"type_43","icon":"clear-night","stations":["72793024233","KSEA","KBFI","72793524234","72793494248","KRNT"],"source":"obs"},{"datetime":"01:00:00","datetimeEpoch":1646902800,"temp":0.5,"feelslike":0.5,"humidity":70.34,"dew":-4.2,"precip":0.0,"precipprob":0.0,"snow":0.0,"snowdepth":0.0,"preciptype":null,"windgust":2.9,"windspeed":1.2,"winddir":34.0,"pressure":1028.3,"visibility":11.0,"cloudcover":0.0,"solarradiation":0.0,"solarenergy":null,"uvindex":0.0,"severerisk":10.0,"conditions":"type_43","icon":"clear-night","stations":["72793024233","KSEA","KBFI","72793524234","72793494248","KRNT"],"source":"obs"},{"datetime":"02:00:00","datetimeEpoch":1646906400,"temp":-1.6,"feelslike":-5.3,"humidity":74.26,"dew":-5.6,"precip":0.0,"precipprob":0.0,"snow":0.0,"snowdepth":0.0,"preciptype":null,"windgust":7.2,"windspeed":10.5,"winddir":150.0,"pressure":1028.1,"visibility":16.0,"cloudcover":0.0,"solarradiation":0.0,"solarenergy":null,"uvindex":0.0,"severerisk":10.0,"conditions":"type_43","icon":"clear-night","stations":["72793024233","KSEA","KBFI","72793524234","72793494248","KRNT"],"source":"obs"},{"datetime":"03:00:00","datetimeEpoch":1646910000,"temp":-0.8,"feelslike":-3.1,"humidity":72.98,"dew":-5.0,"precip":0.0,"precipprob":0.0,"snow":0.0,"snowdepth":0.0,"preciptype":null,"windgust":5.8,"windspeed":6.6,"winddir":126.0,"pressure":1028.2,"visibility":16.0,"cloudcover":0.0,"solarradiation":0.0,"solarenergy":null,"uvindex":0.0,"severerisk":10.0,"conditions":"type_43","icon":"clear-night","stations":["72793024233","KSEA","KBFI","72793524234","72793494248","KRNT"],"source":"obs"},{"datetime":"04:00:00","datetimeEpoch":1646913600,"temp":-0.8,"feelslike":-0.8,"humidity":76.5,"dew":-4.4,"precip":0.0,"precipprob":0.0,"snow":0.0,"snowdepth":0.0,"preciptype":null,"windgust":6.8,"windspeed":1.4,"winddir":34.0,"pressure":1028.2,"visibility":16.0,"cloudcover":0.0,"solarradiation":0.0,"solarenergy":null,"uvindex":0.0,"severerisk":10.0,"conditions":"type_43","icon":"clear-night","stations":["72793024233","KSEA","KBFI","72793524234","72793494248","KRNT"],"source":"obs"},{"datetime":"05:00:00","datetimeEpoch":1646917200,"temp":-1.9,"feelslike":-4.7,"humidity":79.94,"dew":-4.9,"precip":0.0,"precipprob":0.0,"snow":0.0,"snowdepth":0.0,"preciptype":null,"windgust":6.8,"windspeed":7.4,"winddir":150.0,"pressure":1028.4,"visibility":16.0,"cloudcover":0.0,"solarradiation":0.0,"solarenergy":null,"uvindex":0.0,"severerisk":10.0,"conditions":"type_43","icon":"clear-night","stations":["72793024233","KSEA","KBFI","72793524234","72793494248","KRNT"],"source":"obs"},{"datetime":"06:00:00","datetimeEpoch":1646920800,"temp":-1.8,"feelslike":-5.1,"humidity":81.97,"dew":-4.4,"precip":0.0,"precipprob":0.0,"snow":0.0,"snowdepth":0.0,"preciptype":null,"windgust":5.0,"windspeed":8.8,"winddir":143.0,"pressure":1028.2,"visibility":16.0,"cloudcover":13.6,"solarradiation":0.0,"solarenergy":null,"uvindex":0.0,"severerisk":10.0,"conditions":"type_43","icon":"clear-night","stations":["72793024233","KSEA","KBFI","72793524234","72793494248","KRNT"],"source":"obs"},{"datetime":"07:00:00","datetimeEpoch":1646924400,"temp":-1.4,"feelslike":-3.9,"humidity":79.65,"dew":-4.4,"precip":0.0,"precipprob":0.0,"snow":0.0,"snowdepth":0.0,"preciptype":null,"windgust":9.0,"windspeed":6.7,"winddir":147.0,"pressure":1028.5,"visibility":16.0,"cloudcover":13.6,"solarradiation":47.0,"solarenergy":0.2,"uvindex":0.0,"severerisk":10.0,"conditions":"type_43","icon":"clear-day","stations":["72793024233","KSEA","KBFI","72793524234","72793494248","F0821","KRNT"],"source":"obs"},{"datetime":"08:00:00","datetimeEpoch":1646928000,"temp":0.1,"feelslike":0.1,"humidity":77.41,"dew":-3.4,"precip":0.0,"precipprob":0.0,"snow":0.0,"snowdepth":0.0,"preciptype":null,"windgust":9.4,"windspeed":4.2,"winddir":129.0,"pressure":1029.0,"visibility":16.0,"cloudcover":69.6,"solarradiation":162.0,"solarenergy":0.6,"uvindex":2.0,"severerisk":10.0,"conditions":"type_42","icon":"partly-cloudy-day","stations":["72793024233","KSEA","KBFI","72793524234","72793494248","F0821","KRNT"],"source":"obs"},{"datetime":"09:00:00","datetimeEpoch":1646931600,"temp":2.6,"feelslike":0.2,"humidity":66.73,"dew":-3.0,"precip":0.0,"precipprob":0.0,"snow":0.0,"snowdepth":0.0,"preciptype":null,"windgust":6.5,"windspeed":8.7,"winddir":147.0,"pressure":1029.3,"visibility":16.0,"cloudcover":69.6,"solarradiation":304.0,"solarenergy":1.1,"uvindex":3.0,"severerisk":10.0,"conditions":"type_42","icon":"partly-cloudy-day","stations":["72793024233","KSEA","KBFI","72793524234","72793494248","F0821","KRNT"],"source":"obs"},{"datetime":"10:00:00","datetimeEpoch":1646935200,"temp":4.5,"feelslike":2.7,"humidity":56.31,"dew":-3.5,"precip":0.0,"precipprob":0.0,"snow":0.0,"snowdepth":0.0,"preciptype":null,"windgust":8.3,"windspeed":7.6,"winddir":147.0,"pressure":1029.4,"visibility":16.0,"cloudcover":13.6,"solarradiation":486.0,"solarenergy":1.7,"uvindex":5.0,"severerisk":10.0,"conditions":"type_43","icon":"clear-day","stations":["72793024233","KSEA","KBFI","72793524234","72793494248","F0821","KRNT"],"source":"obs"},{"datetime":"11:00:00","datetimeEpoch":1646938800,"temp":6.6,"feelslike":6.6,"humidity":46.82,"dew":-4.0,"precip":0.0,"precipprob":0.0,"snow":0.0,"snowdepth":0.0,"preciptype":null,"windgust":9.7,"windspeed":4.6,"winddir":0.0,"pressure":1029.4,"visibility":16.0,"cloudcover":69.6,"solarradiation":574.0,"solarenergy":2.1,"uvindex":6.0,"severerisk":10.0,"conditions":"type_42","icon":"partly-cloudy-day","stations":["72793024233","KSEA","KBFI","72793524234","72793494248","F0821","KRNT"],"source":"obs"},{"datetime":"12:00:00","datetimeEpoch":1646942400,"temp":7.7,"feelslike":7.7,"humidity":38.9,"dew":-5.5,"precip":0.0,"precipprob":0.0,"snow":0.0,"snowdepth":0.0,"preciptype":null,"windgust":7.9,"windspeed":1.7,"winddir":334.0,"pressure":1029.1,"visibility":16.0,"cloudcover":13.6,"solarradiation":639.0,"solarenergy":2.3,"uvindex":6.0,"severerisk":10.0,"conditions":"type_43","icon":"clear-day","stations":["72793024233","KSEA","KBFI","72793524234","72793494248","F0821","KRNT"],"source":"obs"},{"datetime":"13:00:00","datetimeEpoch":1646946000,"temp":7.8,"feelslike":7.8,"humidity":35.18,"dew":-6.7,"precip":0.0,"precipprob":0.0,"snow":0.0,"snowdepth":0.0,"preciptype":null,"windgust":7.2,"windspeed":2.8,"winddir":331.0,"pressure":1028.5,"visibility":16.0,"cloudcover":13.6,"solarradiation":432.0,"solarenergy":1.6,"uvindex":4.0,"severerisk":10.0,"conditions":"type_43","icon":"clear-day","stations":["72793024233","KSEA","KBFI","72793524234","72793494248","F0821","KRNT"],"source":"obs"},{"datetime":"14:00:00","datetimeEpoch":1646949600,"temp":8.2,"feelslike":7.0,"humidity":31.13,"dew":-7.9,"precip":0.0,"precipprob":0.0,"snow":0.0,"snowdepth":0.0,"preciptype":null,"windgust":7.6,"windspeed":7.4,"winddir":287.0,"pressure":1027.8,"visibility":16.0,"cloudcover":15.3,"solarradiation":282.0,"solarenergy":1.0,"uvindex":3.0,"severerisk":10.0,"conditions":"type_43","icon":"clear-day","stations":["72793024233","KSEA","KBFI","72793524234","72793494248","F0821","KRNT"],"source":"obs"},{"datetime":"15:00:00","datetimeEpoch":1646953200,"temp":8.2,"feelslike":6.8,"humidity":28.85,"dew":-8.9,"precip":0.0,"precipprob":0.0,"snow":0.0,"snowdepth":0.0,"preciptype":null,"windgust":6.1,"windspeed":8.2,"winddir":322.0,"pressure":1027.9,"visibility":16.0,"cloudcover":32.6,"solarradiation":171.0,"solarenergy":0.6,"uvindex":2.0,"severerisk":10.0,"conditions":"type_42","icon":"partly-cloudy-day","stations":["72793024233","KSEA","KBFI","72793524234","72793494248","F0821","KRNT"],"source":"obs"},{"datetime":"16:00:00","datetimeEpoch":1646956800,"temp":7.9,"feelslike":7.9,"humidity":29.11,"dew":-9.1,"precip":0.0,"precipprob":0.0,"snow":0.0,"snowdepth":0.0,"preciptype":null,"windgust":8.3,"windspeed":2.9,"winddir":337.0,"pressure":1028.0,"visibility":16.0,"cloudcover":100.0,"solarradiation":98.0,"solarenergy":0.4,"uvindex":1.0,"severerisk":10.0,"conditions":"type_41","icon":"cloudy","stations":["72793024233","KSEA","KBFI","72793524234","72793494248","F0821","KRNT"],"source":"obs"},{"datetime":"17:00:00","datetimeEpoch":1646960400,"temp":7.9,"feelslike":7.9,"humidity":29.52,"dew":-8.9,"precip":0.0,"precipprob":0.0,"snow":0.0,"snowdepth":0.0,"preciptype":null,"windgust":7.2,"windspeed":0.8,"winddir":334.0,"pressure":1027.6,"visibility":16.0,"cloudcover":100.0,"solarradiation":61.0,"solarenergy":0.2,"uvindex":1.0,"severerisk":10.0,"conditions":"type_41","icon":"cloudy","stations":["72793024233","KSEA","KBFI","72793524234","72793494248","F0821","KRNT"],"source":"obs"},{"datetime":"18:00:00","datetimeEpoch":1646964000,"temp":7.7,"feelslike":7.7,"humidity":30.09,"dew":-8.8,"precip":0.0,"precipprob":0.0,"snow":0.0,"snowdepth":0.0,"preciptype":null,"windgust":4.3,"windspeed":0.0,"winddir":0.0,"pressure":1027.2,"visibility":16.0,"cloudcover":100.0,"solarradiation":20.0,"solarenergy":0.1,"uvindex":0.0,"severerisk":10.0,"conditions":"type_41","icon":"cloudy","stations":["72793024233","KSEA","KBFI","72793524234","72793494248","F0821","KRNT"],"source":"obs"},{"datetime":"19:00:00","datetimeEpoch":1646967600,"temp":7.1,"feelslike":7.1,"humidity":32.17,"dew":-8.4,"precip":0.0,"precipprob":0.0,"snow":0.0,"snowdepth":0.0,"preciptype":null,"windgust":6.8,"windspeed":0.8,"winddir":355.0,"pressure":1027.6,"visibility":16.0,"cloudcover":100.0,"solarradiation":0.0,"solarenergy":null,"uvindex":0.0,"severerisk":10.0,"conditions":"type_41","icon":"cloudy","stations":["72793024233","KSEA","KBFI","72793524234","72793494248","KRNT"],"source":"obs"},{"datetime":"20:00:00","datetimeEpoch":1646971200,"temp":7.0,"feelslike":7.0,"humidity":37.16,"dew":-6.6,"precip":0.0,"precipprob":0.0,"snow":0.0,"snowdepth":0.0,"preciptype":null,"windgust":12.2,"windspeed":0.0,"winddir":0.0,"pressure":1027.7,"visibility":16.0,"cloudcover":100.0,"solarradiation":0.0,"solarenergy":null,"uvindex":0.0,"severerisk":10.0,"conditions":"type_41","icon":"cloudy","stations":["72793024233","KSEA","KBFI","72793524234","72793494248","KRNT"],"source":"obs"},{"datetime":"21:00:00","datetimeEpoch":1646974800,"temp":6.9,"feelslike":6.9,"humidity":41.05,"dew":-5.4,"precip":0.0,"precipprob":0.0,"snow":0.0,"snowdepth":0.0,"preciptype":null,"windgust":15.1,"windspeed":0.0,"winddir":0.0,"pressure":1028.0,"visibility":16.0,"cloudcover":100.0,"solarradiation":0.0,"solarenergy":null,"uvindex":0.0,"severerisk":10.0,"conditions":"type_41","icon":"cloudy","stations":["72793024233","KSEA","KBFI","72793524234","72793494248","KRNT"],"source":"obs"},{"datetime":"22:00:00","datetimeEpoch":1646978400,"temp":6.7,"feelslike":6.7,"humidity":41.22,"dew":-5.6,"precip":0.0,"precipprob":0.0,"snow":0.0,"snowdepth":0.0,"preciptype":null,"windgust":14.8,"windspeed":0.0,"winddir":0.0,"pressure":1028.3,"visibility":16.0,"cloudcover":100.0,"solarradiation":0.0,"solarenergy":null,"uvindex":0.0,"severerisk":10.0,"conditions":"type_41","icon":"cloudy","stations":["72793024233","KSEA","KBFI","72793524234","72793494248","KRNT"],"source":"obs"},{"datetime":"23:00:00","datetimeEpoch":1646982000,"temp":5.9,"feelslike":5.9,"humidity":48.63,"dew":-4.1,"precip":0.0,"precipprob":0.0,"snow":0.0,"snowdepth":0.0,"preciptype":null,"windgust":13.3,"windspeed":2.0,"winddir":34.0,"pressure":1028.3,"visibility":16.0,"cloudcover":100.0,"solarradiation":0.0,"solarenergy":null,"uvindex":0.0,"severerisk":10.0,"conditions":"type_41","icon":"cloudy","stations":["72793024233","KSEA","KBFI","72793524234","72793494248","KRNT"],"source":"obs"}]}],"stations":{"72793024233":{"distance":18063.0,"latitude":47.444,"longitude":-122.314,"useCount":0,"id":"72793024233","name":"SEATTLE TACOMA AIRPORT, WA US","quality":100,"contribution":0.0},"KSEA":{"distance":17555.0,"latitude":47.45,"longitude":-122.3,"useCount":0,"id":"KSEA","name":"KSEA","quality":100,"contribution":0.0},"KBFI":{"distance":8819.0,"latitude":47.53,"longitude":-122.3,"useCount":0,"id":"KBFI","name":"KBFI","quality":100,"contribution":0.0},"72793524234":{"distance":8766.0,"latitude":47.53,"longitude":-122.301,"useCount":0,"id":"72793524234","name":"SEATTLE BOEING FIELD, WA US","quality":100,"contribution":0.0},"72793494248":{"distance":15385.0,"latitude":47.493,"longitude":-122.214,"useCount":0,"id":"72793494248","name":"RENTON MUNICIPAL AIRPORT, WA US","quality":100,"contribution":0.0},"F0821":{"distance":1495.0,"latitude":47.612,"longitude":-122.314,"useCount":0,"id":"F0821","name":"FW0821 Seattle WA US","quality":0,"contribution":0.0},"KRNT":{"distance":14515.0,"latitude":47.5,"longitude":-122.22,"useCount":0,"id":"KRNT","name":"KRNT","quality":100,"contribution":0.0}}}