{"queryCost":24,"latitude":47.6062,"longitude":-122.3321,"resolvedAddress":"47.6062, -122.3321","address":"47.6062, -122.3321","timezone":"America/Los_Angeles","tzoffset":-7.0,"days":[{"datetime":"2020-04-05","datetimeEpoch":1586070000,"tempmax":12.6,"tempmin":7.0,"temp":9.1,"feelslikemax":12.6,"feelslikemin":5.2,"feelslike":8.2,"dew":1.8,"humidity":61.03,"precip":0.0,"precipprob":null,"precipcover":0.0,"preciptype":null,"snow":0.0,"snowdepth":0.0,"windgust":25.9,"windspeed":17.4,"winddir":268.0,"pressure":1003.9,"cloudcover":91.7,"visibility":16.0,"solarradiation":298.6,"solarenergy":15.0,"uvindex":8.0,"sunrise":"06:38:37","sunriseEpoch":1586093917,"sunset":"19:45:53","sunsetEpoch":1586141153,"moonphase":0.45,"conditions":"type_41","description":"Overcast.","icon":"cloudy","stations":["72793024233","KSEA","KBFI","72793524234","72793494248","F0821","KRNT"],"source":"obs","hours":[{"datetime":"00:00:00","datetimeEpoch":1586070000,"temp":7.9,"feelslike":6.2,"humidity":64.56,"dew":1.6,"precip":0.0,"precipprob":null,"snow":0.0,"snowdepth":0.0,"preciptype":null,"windgust":null,"windspeed":9.4,"winddir":357.0,"pressure":1004.1,"visibility":16.0,"cloudcover":100.0,"solarradiation":null,"solarenergy":null,"uvindex":null,"conditions":"type_41","icon":"cloudy","stations":["72793024233","KSEA","KBFI","72793524234","72793494248","KRNT"],"source":"obs"},{"datetime":"01:00:00","datetimeEpoch":1586073600,"temp":7.7,"feelslike":7.7,"humidity":66.14,"dew":1.8,"precip":0.0,"precipprob":null,"snow":0.0,"snowdepth":0.0,"preciptype":null,"windgust":null,"windspeed":3.2,"winddir":7.0,"pressure":1003.6,"visibility":16.0,"cloudcover":95.2,"solarradiation":null,"solarenergy":null,"uvindex":null,"conditions":"type_41","icon":"cloudy","stations":["72793024233","KSEA","KBFI","72793524234"],"source":"obs"},{"datetime":"02:00:00","datetimeEpoch":1586077200,"temp":7.2,"feelslike":5.6,"humidity":69.99,"dew":2.1,"precip":0.0,"precipprob":null,"snow":0.0,"snowdepth":0.0,"preciptype":null,"windgust":null,"windspeed":8.5,"winddir":348.0,"pressure":1003.7,"visibility":16.0,"cloudcover":87.3,"solarradiation":null,"solarenergy":null,"uvindex":null,"conditions":"type_42","icon":"partly-cloudy-night","stations":["72793024233","KSEA","KBFI","72793524234","72793494248","KRNT"],"source":"obs"},{"datetime":"03:00:00","datetimeEpoch":1586080800,"temp":7.6,"feelslike":6.7,"humidity":68.6,"dew":2.2,"precip":0.0,"precipprob":null,"snow":0.0,"snowdepth":0.0,"preciptype":null,"windgust":null,"windspeed":6.0,"winddir":355.0,"pressure":1003.6,"visibility":16.0,"cloudcover":98.6,"solarradiation":null,"solarenergy":null,"uvindex":null,"conditions":"type_41","icon":"cloudy","stations":["72793024233","KSEA","KBFI","72793524234","72793494248","KRNT"],"source":"obs"},{"datetime":"04:00:00","datetimeEpoch":1586084400,"temp":7.1,"feelslike":5.3,"humidity":71.41,"dew":2.3,"precip":0.0,"precipprob":null,"snow":0.0,"snowdepth":0.0,"preciptype":null,"windgust":null,"windspeed":9.8,"winddir":334.0,"pressure":1003.3,"visibility":16.0,"cloudcover":100.0,"solarradiation":null,"solarenergy":null,"uvindex":null,"conditions":"type_41","icon":"cloudy","stations":["72793024233","KSEA","KBFI","72793524234","72793494248","KRNT"],"source":"obs"},{"datetime":"05:00:00","datetimeEpoch":1586088000,"temp":7.0,"feelslike":5.2,"humidity":71.95,"dew":2.3,"precip":0.0,"precipprob":null,"snow":0.0,"snowdepth":0.0,"preciptype":null,"windgust":null,"windspeed":9.6,"winddir":352.0,"pressure":1003.3,"visibility":16.0,"cloudcover":100.0,"solarradiation":null,"solarenergy":null,"uvindex":null,"conditions":"type_41","icon":"cloudy","stations":["72793024233","KSEA","KBFI","72793524234","72793494248","KRNT"],"source":"obs"},{"datetime":"06:00:00","datetimeEpoch":1586091600,"temp":7.0,"feelslike":5.4,"humidity":74.07,"dew":2.7,"precip":0.0,"precipprob":null,"snow":0.0,"snowdepth":0.0,"preciptype":null,"windgust":null,"windspeed":8.6,"winddir":358.0,"pressure":1003.3,"visibility":16.0,"cloudcover":97.7,"solarradiation":null,"solarenergy":null,"uvindex":null,"conditions":"type_41","icon":"cloudy","stations":["72793024233","KSEA","KBFI","72793524234","72793494248","KRNT"],"source":"obs"},{"datetime":"07:00:00","datetimeEpoch":1586095200,"temp":7.1,"feelslike":7.1,"humidity":74.37,"dew":2.9,"precip":0.0,"precipprob":null,"snow":0.0,"snowdepth":0.0,"preciptype":null,"windgust":null,"windspeed":4.0,"winddir":7.0,"pressure":1003.5,"visibility":16.0,"cloudcover":98.8,"solarradiation":9.0,"solarenergy":0.0,"uvindex":0.0,"conditions":"type_41","icon":"cloudy","stations":["72793024233","KSEA","KBFI","72793524234","F0821"],"source":"obs"},{"datetime":"08:00:00","datetimeEpoch":1586098800,"temp":7.0,"feelslike":5.9,"humidity":75.56,"dew":3.0,"precip":0.0,"precipprob":null,"snow":0.0,"snowdepth":0.0,"preciptype":null,"windgust":null,"windspeed":6.6,"winddir":358.0,"pressure":1003.8,"visibility":16.0,"cloudcover":82.0,"solarradiation":46.0,"solarenergy":0.2,"uvindex":0.0,"conditions":"type_42","icon":"partly-cloudy-day","stations":["72793024233","KSEA","KBFI","72793524234","72793494248","F0821","KRNT"],"source":"obs"},{"datetime":"09:00:00","datetimeEpoch":1586102400,"temp":7.6,"feelslike":5.9,"humidity":73.12,"dew":3.1,"precip":0.0,"precipprob":null,"snow":0.0,"snowdepth":0.0,"preciptype":null,"windgust":null,"windspeed":9.6,"winddir":2.0,"pressure":1003.9,"visibility":16.0,"cloudcover":96.3,"solarradiation":109.0,"solarenergy":0.4,"uvindex":1.0,"conditions":"type_41","icon":"cloudy","stations":["72793024233","KSEA","KBFI","72793524234","72793494248","F0821","KRNT"],"source":"obs"},{"datetime":"10:00:00","datetimeEpoch":1586106000,"temp":8.6,"feelslike":7.1,"humidity":63.35,"dew":2.0,"precip":0.0,"precipprob":null,"snow":0.0,"snowdepth":0.0,"preciptype":null,"windgust":null,"windspeed":9.0,"winddir":4.0,"pressure":1003.8,"visibility":16.0,"cloudcover":95.3,"solarradiation":272.0,"solarenergy":1.0,"uvindex":3.0,"conditions":"type_41","icon":"cloudy","stations":["72793024233","KSEA","KBFI","72793524234","72793494248","F0821","KRNT"],"source":"obs"},{"datetime":"11:00:00","datetimeEpoch":1586109600,"temp":10.2,"feelslike":10.2,"humidity":55.75,"dew":1.7,"precip":0.0,"precipprob":null,"snow":0.0,"snowdepth":0.0,"preciptype":null,"windgust":null,"windspeed":12.7,"winddir":342.0,"pressure":1003.9,"visibility":16.0,"cloudcover":94.7,"solarradiation":375.0,"solarenergy":1.4,"uvindex":4.0,"conditions":"type_41","icon":"cloudy","stations":["72793024233","KSEA","KBFI","72793524234","72793494248","F0821","KRNT"],"source":"obs"},{"datetime":"12:00:00","datetimeEpoch":1586113200,"temp":10.8,"feelslike":10.8,"humidity":56.28,"dew":2.4,"precip":0.0,"precipprob":null,"snow":0.0,"snowdepth":0.0,"preciptype":null,"windgust":null,"windspeed":14.3,"winddir":320.0,"pressure":1003.8,"visibility":16.0,"cloudcover":89.1,"solarradiation":757.0,"solarenergy":2.7,"uvindex":8.0,"conditions":"type_42","icon":"partly-cloudy-day","stations":["72793024233","KSEA","KBFI","72793524234","72793494248","F0821","KRNT"],"source":"obs"},{"datetime":"13:00:00","datetimeEpoch":1586116800,"temp":11.2,"feelslike":11.2,"humidity":52.95,"dew":2.0,"precip":0.0,"precipprob":null,"snow":0.0,"snowdepth":0.0,"preciptype":null,"windgust":null,"windspeed":16.9,"winddir":325.0,"pressure":1003.6,"visibility":16.0,"cloudcover":96.1,"solarradiation":700.0,"solarenergy":2.5,"uvindex":7.0,"conditions":"type_41","icon":"cloudy","stations":["72793024233","KSEA","KBFI","72793524234","72793494248","F0821","KRNT"],"source":"obs"},{"datetime":"14:00:00","datetimeEpoch":1586120400,"temp":12.1,"feelslike":12.1,"humidity":49.68,"dew":1.9,"precip":0.0,"precipprob":null,"snow":0.0,"snowdepth":0.0,"preciptype":null,"windgust":null,"windspeed":17.4,"winddir":309.0,"pressure":1003.2,"visibility":16.0,"cloudcover":89.6,"solarradiation":542.0,"solarenergy":2.0,"uvindex":5.0,"conditions":"type_42","icon":"partly-cloudy-day","stations":["72793024233","KSEA","KBFI","72793524234","72793494248","F0821","KRNT"],"source":"obs"},{"datetime":"15:00:00","datetimeEpoch":1586124000,"temp":12.6,"feelslike":12.6,"humidity":46.88,"dew":1.5,"precip":0.0,"precipprob":null,"snow":0.0,"snowdepth":0.0,"preciptype":null,"windgust":null,"windspeed":15.5,"winddir":327.0,"pressure":1003.1,"visibility":16.0,"cloudcover":77.7,"solarradiation":621.0,"solarenergy":2.2,"uvindex":6.0,"conditions":"type_42","icon":"partly-cloudy-day","stations":["72793024233","KSEA","KBFI","72793524234","72793494248","F0821","KRNT"],"source":"obs"},{"datetime":"16:00:00","datetimeEpoch":1586127600,"temp":12.5,"feelslike":12.5,"humidity":45.52,"dew":1.0,"precip":0.0,"precipprob":null,"snow":0.0,"snowdepth":0.0,"preciptype":null,"windgust":null,"windspeed":15.4,"winddir":327.0,"pressure":1003.3,"visibility":16.0,"cloudcover":87.2,"solarradiation":473.0,"solarenergy":1.7,"uvindex":5.0,"conditions":"type_42","icon":"partly-cloudy-day","stations":["72793024233","KSEA","KBFI","72793524234","72793494248","F0821","KRNT"],"source":"obs"},{"datetime":"17:00:00","datetimeEpoch":1586131200,"temp":11.8,"feelslike":11.8,"humidity":46.91,"dew":0.8,"precip":0.0,"precipprob":null,"snow":0.0,"snowdepth":0.0,"preciptype":null,"windgust":null,"windspeed":17.2,"winddir":317.0,"pressure":1003.5,"visibility":16.0,"cloudcover":98.3,"solarradiation":156.0,"solarenergy":0.6,"uvindex":2.0,"conditions":"type_41","icon":"cloudy","stations":["72793024233","KSEA","KBFI","72793524234","72793494248","F0821","KRNT"],"source":"obs"},{"datetime":"18:00:00","datetimeEpoch":1586134800,"temp":10.7,"feelslike":10.7,"humidity":49.37,"dew":0.5,"precip":0.0,"precipprob":null,"snow":0.0,"snowdepth":0.0,"preciptype":null,"windgust":25.9,"windspeed":15.8,"winddir":335.0,"pressure":1003.9,"visibility":16.0,"cloudcover":100.0,"solarradiation":69.0,"solarenergy":0.2,"uvindex":1.0,"conditions":"type_41","icon":"cloudy","stations":["72793024233","KSEA","KBFI","72793524234","72793494248","F0821","KRNT"],"source":"obs"},{"datetime":"19:00:00","datetimeEpoch":1586138400,"temp":9.8,"feelslike":7.5,"humidity":55.84,"dew":1.4,"precip":0.0,"precipprob":null,"snow":0.0,"snowdepth":0.0,"preciptype":null,"windgust":null,"windspeed":16.4,"winddir":352.0,"pressure":1004.3,"visibility":16.0,"cloudcover":90.5,"solarradiation":38.0,"solarenergy":0.1,"uvindex":0.0,"conditions":"type_41","icon":"cloudy","stations":["72793024233","KSEA","KBFI","72793524234","72793494248","F0821","KRNT"],"source":"obs"},{"datetime":"20:00:00","datetimeEpoch":1586142000,"temp":9.3,"feelslike":7.4,"humidity":59.46,"dew":1.8,"precip":0.0,"precipprob":null,"snow":0.0,"snowdepth":0.0,"preciptype":null,"windgust":null,"windspeed":12.1,"winddir":317.0,"pressure":1004.5,"visibility":16.0,"cloudcover":95.3,"solarradiation":13.0,"solarenergy":0.0,"uvindex":0.0,"conditions":"type_41","icon":"cloudy","stations":["72793024233","KSEA","KBFI","72793524234","72793494248","F0821","KRNT"],"source":"obs"},{"datetime":"21:00:00","datetimeEpoch":1586145600,"temp":9.1,"feelslike":7.7,"humidity":59.47,"dew":1.6,"precip":0.0,"precipprob":null,"snow":0.0,"snowdepth":0.0,"preciptype":null,"windgust":null,"windspeed":9.3,"winddir":338.0,"pressure":1005.0,"visibility":16.0,"cloudcover":61.7,"solarradiation":null,"solarenergy":null,"uvindex":null,"conditions":"type_42","icon":"partly-cloudy-night","stations":["72793024233","KSEA","KBFI","72793524234","72793494248","KRNT"],"source":"obs"},{"datetime":"22:00:00","datetimeEpoch":1586149200,"temp":8.6,"feelslike":7.0,"humidity":59.54,"dew":1.1,"precip":0.0,"precipprob":null,"snow":0.0,"snowdepth":0.0,"preciptype":null,"windgust":null,"windspeed":10.0,"winddir":334.0,"pressure":1005.9,"visibility":16.0,"cloudcover":91.4,"solarradiation":null,"solarenergy":null,"uvindex":null,"conditions":"type_41","icon":"cloudy","stations":["72793024233","KSEA","KBFI","72793524234","72793494248","KRNT"],"source":"obs"},{"datetime":"23:00:00","datetimeEpoch":1586152800,"temp":9.0,"feelslike":7.3,"humidity":53.91,"dew":0.1,"precip":0.0,"precipprob":null,"snow":0.0,"snowdepth":0.0,"preciptype":null,"windgust":null,"windspeed":10.5,"winddir":6.0,"pressure":1006.5,"visibility":16.0,"cloudcover":78.3,"solarradiation":null,"solarenergy":null,"uvindex":null,"conditions":"type_42","icon":"partly-cloudy-night","stations":["72793024233","KSEA","KBFI","72793524234","72793494248","KRNT"],"source":"obs"}]}],"stations":{"72793024233":{"distance":18063.0,"latitude":47.444,"longitude":-122.314,"useCount":0,"id":"72793024233","name":"SEATTLE TACOMA AIRPORT, WA US","quality":100,"contribution":0.0},"KSEA":{"distance":17555.0,"latitude":47.45,"longitude":-122.3,"useCount":0,"id":"KSEA","name":"KSEA","quality":100,"contribution":0.0},"KBFI":{"distance":8819.0,"latitude":47.53,"longitude":-122.3,"useCount":0,"id":"KBFI","name":"KBFI","quality":100,"contribution":0.0},"72793524234":{"distance":8766.0,"latitude":47.53,"longitude":-122.301,"useCount":0,"id":"72793524234","name":"SEATTLE BOEING FIELD, WA US","quality":100,"contribution":0.0},"72793494248":{"distance":15385.0,"latitude":47.493,"longitude":-122.214,"useCount":0,"id":"72793494248","name":"RENTON MUNICIPAL AIRPORT, WA US","quality":100,"contribution":0.0},"F0821":{"distance":1495.0,"latitude":47.612,"longitude":-122.314,"useCount":0,"id":"F0821","name":"FW0821 Seattle WA US","quality":0,"contribution":0.0},"KRNT":{"distance":14515.0,"latitude":47.5,"longitude":-122.22,"useCount":0,"id":"KRNT","name":"KRNT","quality":100,"contribution":0.0}}}