{"queryCost":24,"latitude":47.6062,"longitude":-122.3321,"resolvedAddress":"47.6062, -122.3321","address":"47.6062, -122.3321","timezone":"America/Los_Angeles","tzoffset":-7.0,"days":[{"datetime":"2019-05-21","datetimeEpoch":1558422000,"tempmax":16.5,"tempmin":11.0,"temp":13.6,"feelslikemax":16.5,"feelslikemin":11.0,"feelslike":13.6,"dew":8.7,"humidity":72.88,"precip":0.08,"precipprob":null,"precipcover":8.33,"preciptype":null,"snow":0.0,"snowdepth":0.0,"windgust":null,"windspeed":12.9,"winddir":109.0,"pressure":1007.9,"cloudcover":83.2,"visibility":14.9,"solarradiation":195.5,"solarenergy":11.3,"uvindex":4.0,"sunrise":"05:25:10","sunriseEpoch":1558441510,"sunset":"20:47:26","sunsetEpoch":1558496846,"moonphase":0.54,"conditions":"type_21, type_42","description":"Variablecloud with rainearlyam.","icon":"rain","stations":["72793024233","E8003","KSEA","KBFI","72793524234","72793494248","KRNT"],"source":"obs","hours":[{"datetime":"00:00:00","datetimeEpoch":1558422000,"temp":11.4,"feelslike":11.4,"humidity":75.29,"dew":7.2,"precip":0.0,"precipprob":null,"snow":0.0,"snowdepth":0.0,"preciptype":null,"windgust":null,"windspeed":7.8,"winddir":112.0,"pressure":1006.6,"visibility":14.9,"cloudcover":100.0,"solarradiation":null,"solarenergy":null,"uvindex":null,"conditions":"type_41","icon":"cloudy","stations":["72793024233","KSEA","KBFI","72793524234","72793494248","KRNT"],"source":"obs"},{"datetime":"01:00:00","datetimeEpoch":1558425600,"temp":11.0,"feelslike":11.0,"humidity":81.53,"dew":8.0,"precip":0.0,"precipprob":null,"snow":0.0,"snowdepth":0.0,"preciptype":null,"windgust":null,"windspeed":1.7,"winddir":11.0,"pressure":1006.3,"visibility":14.9,"cloudcover":99.1,"solarradiation":null,"solarenergy":null,"uvindex":null,"conditions":"type_41","icon":"cloudy","stations":["72793024233","KSEA","KBFI","72793524234","72793494248","KRNT"],"source":"obs"},{"datetime":"02:00:00","datetimeEpoch":1558429200,"temp":11.1,"feelslike":11.1,"humidity":78.95,"dew":7.6,"precip":0.0,"precipprob":null,"snow":0.0,"snowdepth":0.0,"preciptype":null,"windgust":null,"windspeed":3.6,"winddir":4.0,"pressure":1006.0,"visibility":15.3,"cloudcover":94.1,"solarradiation":null,"solarenergy":null,"uvindex":null,"conditions":"type_41","icon":"cloudy","stations":["72793024233","KSEA","KBFI","72793524234","72793494248","KRNT"],"source":"obs"},{"datetime":"03:00:00","datetimeEpoch":1558432800,"temp":11.0,"feelslike":11.0,"humidity":82.32,"dew":8.1,"precip":0.0,"precipprob":null,"snow":0.0,"snowdepth":0.0,"preciptype":null,"windgust":null,"windspeed":1.4,"winddir":11.0,"pressure":1006.0,"visibility":14.9,"cloudcover":70.7,"solarradiation":null,"solarenergy":null,"uvindex":null,"conditions":"type_42","icon":"partly-cloudy-night","stations":["72793024233","KSEA","KBFI","72793524234","72793494248","KRNT"],"source":"obs"},{"datetime":"04:00:00","datetimeEpoch":1558436400,"temp":11.0,"feelslike":11.0,"humidity":82.93,"dew":8.2,"precip":0.06,"precipprob":null,"snow":0.0,"snowdepth":0.0,"preciptype":null,"windgust":null,"windspeed":1.2,"winddir":360.0,"pressure":1005.8,"visibility":14.9,"cloudcover":99.1,"solarradiation":null,"solarenergy":null,"uvindex":null,"conditions":"type_21, type_41","icon":"rain","stations":["72793024233","KSEA","KBFI","72793524234","72793494248","KRNT"],"source":"obs"},{"datetime":"05:00:00","datetimeEpoch":1558440000,"temp":11.0,"feelslike":11.0,"humidity":83.37,"dew":8.3,"precip":0.02,"precipprob":null,"snow":0.0,"snowdepth":0.0,"preciptype":null,"windgust":null,"windspeed":1.4,"winddir":8.0,"pressure":1005.8,"visibility":14.9,"cloudcover":93.9,"solarradiation":null,"solarenergy":null,"uvindex":null,"conditions":"type_21, type_41","icon":"rain","stations":["72793024233","KSEA","KBFI","72793524234","72793494248","KRNT"],"source":"obs"},{"datetime":"06:00:00","datetimeEpoch":1558443600,"temp":11.0,"feelslike":11.0,"humidity":85.16,"dew":8.6,"precip":0.0,"precipprob":null,"snow":0.0,"snowdepth":0.0,"preciptype":null,"windgust":null,"windspeed":4.8,"winddir":29.0,"pressure":1006.1,"visibility":15.3,"cloudcover":87.4,"solarradiation":7.0,"solarenergy":0.0,"uvindex":0.0,"conditions":"type_42","icon":"partly-cloudy-day","stations":["E8003","72793024233","KSEA","KBFI","72793524234","72793494248","KRNT"],"source":"obs"},{"datetime":"07:00:00","datetimeEpoch":1558447200,"temp":11.1,"feelslike":11.1,"humidity":83.2,"dew":8.3,"precip":0.0,"precipprob":null,"snow":0.0,"snowdepth":0.0,"preciptype":null,"windgust":null,"windspeed":1.2,"winddir":357.0,"pressure":1006.5,"visibility":14.7,"cloudcover":64.9,"solarradiation":11.0,"solarenergy":0.0,"uvindex":0.0,"conditions":"type_42","icon":"partly-cloudy-day","stations":["E8003","72793024233","KSEA","KBFI","72793524234","72793494248","KRNT"],"source":"obs"},{"datetime":"08:00:00","datetimeEpoch":1558450800,"temp":11.5,"feelslike":11.5,"humidity":82.22,"dew":8.6,"precip":0.0,"precipprob":null,"snow":0.0,"snowdepth":0.0,"preciptype":null,"windgust":null,"windspeed":2.3,"winddir":8.0,"pressure":1006.5,"visibility":14.9,"cloudcover":67.8,"solarradiation":74.0,"solarenergy":0.3,"uvindex":1.0,"conditions":"type_42","icon":"partly-cloudy-day","stations":["E8003","72793024233","KSEA","KBFI","72793524234","72793494248","KRNT"],"source":"obs"},{"datetime":"09:00:00","datetimeEpoch":1558454400,"temp":12.2,"feelslike":12.2,"humidity":78.48,"dew":8.6,"precip":0.0,"precipprob":null,"snow":0.0,"snowdepth":0.0,"preciptype":null,"windgust":null,"windspeed":9.4,"winddir":31.0,"pressure":1006.9,"visibility":14.9,"cloudcover":58.7,"solarradiation":135.0,"solarenergy":0.5,"uvindex":1.0,"conditions":"type_42","icon":"partly-cloudy-day","stations":["E8003","72793024233","KSEA","KBFI","72793524234","72793494248","KRNT"],"source":"obs"},{"datetime":"10:00:00","datetimeEpoch":1558458000,"temp":12.7,"feelslike":12.7,"humidity":78.14,"dew":9.0,"precip":0.0,"precipprob":null,"snow":0.0,"snowdepth":0.0,"preciptype":null,"windgust":null,"windspeed":12.2,"winddir":4.0,"pressure":1007.2,"visibility":14.9,"cloudcover":72.1,"solarradiation":218.0,"solarenergy":0.8,"uvindex":2.0,"conditions":"type_42","icon":"partly-cloudy-day","stations":["E8003","72793024233","KSEA","KBFI","72793524234","72793494248","KRNT"],"source":"obs"},{"datetime":"11:00:00","datetimeEpoch":1558461600,"temp":13.7,"feelslike":13.7,"humidity":73.23,"dew":9.0,"precip":0.0,"precipprob":null,"snow":0.0,"snowdepth":0.0,"preciptype":null,"windgust":null,"windspeed":10.6,"winddir":358.0,"pressure":1007.5,"visibility":14.9,"cloudcover":79.5,"solarradiation":446.0,"solarenergy":1.6,"uvindex":4.0,"conditions":"type_42","icon":"partly-cloudy-day","stations":["E8003","72793024233","KSEA","KBFI","72793524234","72793494248","KRNT"],"source":"obs"},{"datetime":"12:00:00","datetimeEpoch":1558465200,"temp":14.3,"feelslike":14.3,"humidity":69.22,"dew":8.7,"precip":0.0,"precipprob":null,"snow":0.0,"snowdepth":0.0,"preciptype":null,"windgust":null,"windspeed":7.1,"winddir":338.0,"pressure":1007.6,"visibility":14.9,"cloudcover":86.4,"solarradiation":288.0,"solarenergy":1.0,"uvindex":3.0,"conditions":"type_42","icon":"partly-cloudy-day","stations":["E8003","72793024233","KSEA","KBFI","72793524234","72793494248","KRNT"],"source":"obs"},{"datetime":"13:00:00","datetimeEpoch":1558468800,"temp":14.7,"feelslike":14.7,"humidity":66.55,"dew":8.6,"precip":0.0,"precipprob":null,"snow":0.0,"snowdepth":0.0,"preciptype":null,"windgust":null,"windspeed":10.3,"winddir":20.0,"pressure":1008.0,"visibility":14.9,"cloudcover":89.6,"solarradiation":323.0,"solarenergy":1.2,"uvindex":3.0,"conditions":"type_42","icon":"partly-cloudy-day","stations":["E8003","72793024233","KSEA","KBFI","72793524234","72793494248","KRNT"],"source":"obs"},{"datetime":"14:00:00","datetimeEpoch":1558472400,"temp":15.4,"feelslike":15.4,"humidity":64.59,"dew":8.8,"precip":0.0,"precipprob":null,"snow":0.0,"snowdepth":0.0,"preciptype":null,"windgust":null,"windspeed":12.4,"winddir":342.0,"pressure":1008.2,"visibility":14.9,"cloudcover":94.6,"solarradiation":373.0,"solarenergy":1.3,"uvindex":4.0,"conditions":"type_41","icon":"cloudy","stations":["E8003","72793024233","KSEA","KBFI","72793524234","72793494248","KRNT"],"source":"obs"},{"datetime":"15:00:00","datetimeEpoch":1558476000,"temp":15.4,"feelslike":15.4,"humidity":64.34,"dew":8.7,"precip":0.0,"precipprob":null,"snow":0.0,"snowdepth":0.0,"preciptype":null,"windgust":null,"windspeed":12.9,"winddir":352.0,"pressure":1008.5,"visibility":14.7,"cloudcover":98.3,"solarradiation":285.0,"solarenergy":1.0,"uvindex":3.0,"conditions":"type_41","icon":"cloudy","stations":["E8003","72793024233","KSEA","KBFI","72793524234","72793494248","KRNT"],"source":"obs"},{"datetime":"16:00:00","datetimeEpoch":1558479600,"temp":16.3,"feelslike":16.3,"humidity":62.04,"dew":9.0,"precip":0.0,"precipprob":null,"snow":0.0,"snowdepth":0.0,"preciptype":null,"windgust":null,"windspeed":9.5,"winddir":60.0,"pressure":1008.6,"visibility":14.7,"cloudcover":91.4,"solarradiation":315.0,"solarenergy":1.1,"uvindex":3.0,"conditions":"type_41","icon":"cloudy","stations":["E8003","72793024233","KSEA","KBFI","72793524234","72793494248","KRNT"],"source":"obs"},{"datetime":"17:00:00","datetimeEpoch":1558483200,"temp":16.5,"feelslike":16.5,"humidity":62.22,"dew":9.2,"precip":0.0,"precipprob":null,"snow":0.0,"snowdepth":0.0,"preciptype":null,"windgust":null,"windspeed":7.1,"winddir":7.0,"pressure":1008.8,"visibility":14.7,"cloudcover":71.0,"solarradiation":263.0,"solarenergy":0.9,"uvindex":3.0,"conditions":"type_42","icon":"partly-cloudy-day","stations":["E8003","72793024233","KSEA","KBFI","72793524234","72793494248","KRNT"],"source":"obs"},{"datetime":"18:00:00","datetimeEpoch":1558486800,"temp":16.5,"feelslike":16.5,"humidity":61.63,"dew":9.1,"precip":0.0,"precipprob":null,"snow":0.0,"snowdepth":0.0,"preciptype":null,"windgust":null,"windspeed":8.1,"winddir":20.0,"pressure":1009.1,"visibility":14.7,"cloudcover":61.3,"solarradiation":169.0,"solarenergy":0.6,"uvindex":2.0,"conditions":"type_42","icon":"partly-cloudy-day","stations":["E8003","72793024233","KSEA","KBFI","72793524234","72793494248","KRNT"],"source":"obs"},{"datetime":"19:00:00","datetimeEpoch":1558490400,"temp":16.2,"feelslike":16.2,"humidity":63.6,"dew":9.2,"precip":0.0,"precipprob":null,"snow":0.0,"snowdepth":0.0,"preciptype":null,"windgust":null,"windspeed":9.9,"winddir":2.0,"pressure":1009.5,"visibility":14.3,"cloudcover":69.9,"solarradiation":111.0,"solarenergy":0.4,"uvindex":1.0,"conditions":"type_42","icon":"partly-cloudy-day","stations":["E8003","72793024233","KSEA","KBFI","72793524234","72793494248","KRNT"],"source":"obs"},{"datetime":"20:00:00","datetimeEpoch":1558494000,"temp":16.1,"feelslike":16.1,"humidity":64.99,"dew":9.5,"precip":0.0,"precipprob":null,"snow":0.0,"snowdepth":0.0,"preciptype":null,"windgust":null,"windspeed":1.4,"winddir":11.0,"pressure":1010.1,"visibility":14.7,"cloudcover":69.9,"solarradiation":95.0,"solarenergy":0.3,"uvindex":1.0,"conditions":"type_42","icon":"partly-cloudy-day","stations":["E8003","72793024233","KSEA","KBFI","72793524234","72793494248","KRNT"],"source":"obs"},{"datetime":"21:00:00","datetimeEpoch":1558497600,"temp":15.6,"feelslike":15.6,"humidity":65.46,"dew":9.1,"precip":0.0,"precipprob":null,"snow":0.0,"snowdepth":0.0,"preciptype":null,"windgust":null,"windspeed":5.9,"winddir":79.0,"pressure":1010.8,"visibility":14.7,"cloudcover":86.4,"solarradiation":15.0,"solarenergy":0.1,"uvindex":0.0,"conditions":"type_42","icon":"partly-cloudy-night","stations":["E8003","72793024233","KSEA","KBFI","72793524234","72793494248","KRNT"],"source":"obs"},{"datetime":"22:00:00","datetimeEpoch":1558501200,"temp":14.9,"feelslike":14.9,"humidity":70.07,"dew":9.5,"precip":0.0,"precipprob":null,"snow":0.0,"snowdepth":0.0,"preciptype":null,"windgust":null,"windspeed":0.0,"winddir":0.0,"pressure":1011.6,"visibility":14.9,"cloudcover":91.4,"solarradiation":null,"solarenergy":null,"uvindex":null,"conditions":"type_41","icon":"cloudy","stations":["72793024233","KSEA","KBFI","72793524234","72793494248","KRNT"],"source":"obs"},{"datetime":"23:00:00","datetimeEpoch":1558504800,"temp":15.2,"feelslike":15.2,"humidity":69.54,"dew":9.6,"precip":0.0,"precipprob":null,"snow":0.0,"snowdepth":0.0,"preciptype":null,"windgust":null,"windspeed":3.4,"winddir":92.0,"pressure":1012.1,"visibility":14.9,"cloudcover":100.0,"solarradiation":null,"solarenergy":null,"uvindex":null,"conditions":"type_41","icon":"cloudy","stations":["72793024233","KSEA","KBFI","72793524234","72793494248","KRNT"],"source":"obs"}]}],"stations":{"72793024233":{"distance":18063.0,"latitude":47.444,"longitude":-122.314,"useCount":0,"id":"72793024233","name":"SEATTLE TACOMA AIRPORT, WA US","quality":100,"contribution":0.0},"E8003":{"distance":5596.0,"latitude":47.654,"longitude":-122.309,"useCount":0,"id":"E8003","name":"EW8003 Seattle WA US","quality":0,"contribution":0.0},"KSEA":{"distance":17555.0,"latitude":47.45,"longitude":-122.3,"useCount":0,"id":"KSEA","name":"KSEA","quality":100,"contribution":0.0},"KBFI":{"distance":8819.0,"latitude":47.53,"longitude":-122.3,"useCount":0,"id":"KBFI","name":"KBFI","quality":100,"contribution":0.0},"72793524234":{"distance":8766.0,"latitude":47.53,"longitude":-122.301,"useCount":0,"id":"72793524234","name":"SEATTLE BOEING FIELD, WA US","quality":100,"contribution":0.0},"72793494248":{"distance":15385.0,"latitude":47.493,"longitude":-122.214,"useCount":0,"id":"72793494248","name":"RENTON MUNICIPAL AIRPORT, WA US","quality":100,"contribution":0.0},"KRNT":{"distance":14515.0,"latitude":47.5,"longitude":-122.22,"useCount":0,"id":"KRNT","name":"KRNT","quality":100,"contribution":0.0}}}