{"queryCost":24,"latitude":47.6062,"longitude":-122.3321,"resolvedAddress":"47.6062, -122.3321","address":"47.6062, -122.3321","timezone":"America/Los_Angeles","tzoffset":-8.0,"days":[{"datetime":"2019-11-04","datetimeEpoch":1572854400,"tempmax":13.4,"tempmin":5.1,"temp":8.8,"feelslikemax":13.4,"feelslikemin":4.4,"feelslike":8.6,"dew":5.4,"humidity":79.95,"precip":0.0,"precipprob":null,"precipcover":0.0,"preciptype":null,"snow":0.0,"snowdepth":0.0,"windgust":null,"windspeed":11.0,"winddir":176.6,"pressure":1023.4,"cloudcover":47.3,"visibility":14.2,"solarradiation":138.5,"solarenergy":6.0,"uvindex":4.0,"sunrise":"06:57:45","sunriseEpoch":1572879465,"sunset":"16:47:21","sunsetEpoch":1572914841,"moonphase":0.25,"conditions":"type_42","description":"Variablecloud.","icon":"partly-cloudy-day","stations":["F4154","72793024233","KSEA","KBFI","E8046","72793524234","72793494248","F0821","KRNT"],"source":"obs","hours":[{"datetime":"00:00:00","datetimeEpoch":1572854400,"temp":7.3,"feelslike":6.7,"humidity":85.79,"dew":5.0,"precip":0.0,"precipprob":null,"snow":0.0,"snowdepth":0.0,"preciptype":null,"windgust":null,"windspeed":4.8,"winddir":360.0,"pressure":1023.5,"visibility":13.5,"cloudcover":0.0,"solarradiation":403.0,"solarenergy":1.5,"uvindex":4.0,"conditions":"type_43","icon":"clear-night","stations":["F4154","72793024233","KSEA","KBFI","72793524234","72793494248","KRNT"],"source":"obs"},{"datetime":"01:00:00","datetimeEpoch":1572858000,"temp":6.2,"feelslike":6.2,"humidity":86.34,"dew":4.1,"precip":0.0,"precipprob":null,"snow":0.0,"snowdepth":0.0,"preciptype":null,"windgust":null,"windspeed":1.7,"winddir":360.0,"pressure":1023.6,"visibility":11.3,"cloudcover":0.0,"solarradiation":null,"solarenergy":null,"uvindex":null,"conditions":"type_43","icon":"clear-night","stations":["72793024233","KSEA","KBFI","72793524234","72793494248","KRNT"],"source":"obs"},{"datetime":"02:00:00","datetimeEpoch":1572861600,"temp":5.5,"feelslike":5.5,"humidity":89.15,"dew":3.9,"precip":0.0,"precipprob":null,"snow":0.0,"snowdepth":0.0,"preciptype":null,"windgust":null,"windspeed":2.3,"winddir":5.0,"pressure":1023.5,"visibility":9.5,"cloudcover":0.0,"solarradiation":null,"solarenergy":null,"uvindex":null,"conditions":"type_43","icon":"clear-night","stations":["72793024233","KSEA","KBFI","72793524234","72793494248","KRNT"],"source":"obs"},{"datetime":"03:00:00","datetimeEpoch":1572865200,"temp":5.1,"feelslike":5.1,"humidity":90.41,"dew":3.7,"precip":0.0,"precipprob":null,"snow":0.0,"snowdepth":0.0,"preciptype":null,"windgust":null,"windspeed":2.2,"winddir":52.0,"pressure":1023.7,"visibility":9.4,"cloudcover":53.0,"solarradiation":null,"solarenergy":null,"uvindex":null,"conditions":"type_42","icon":"partly-cloudy-night","stations":["KSEA","KBFI","72793524234","72793494248","KRNT"],"source":"obs"},{"datetime":"04:00:00","datetimeEpoch":1572868800,"temp":6.5,"feelslike":6.5,"humidity":88.45,"dew":4.7,"precip":0.0,"precipprob":null,"snow":0.0,"snowdepth":0.0,"preciptype":null,"windgust":null,"windspeed":1.4,"winddir":11.0,"pressure":1023.3,"visibility":11.0,"cloudcover":60.2,"solarradiation":null,"solarenergy":null,"uvindex":null,"conditions":"type_42","icon":"partly-cloudy-night","stations":["72793024233","KSEA","KBFI","72793524234","72793494248","KRNT"],"source":"obs"},{"datetime":"05:00:00","datetimeEpoch":1572872400,"temp":6.3,"feelslike":5.5,"humidity":87.53,"dew":4.4,"precip":0.0,"precipprob":null,"snow":0.0,"snowdepth":0.0,"preciptype":null,"windgust":null,"windspeed":5.1,"winddir":114.0,"pressure":1023.3,"visibility":12.2,"cloudcover":97.6,"solarradiation":null,"solarenergy":null,"uvindex":null,"conditions":"type_41","icon":"cloudy","stations":["72793024233","KSEA","KBFI","72793524234","72793494248","KRNT"],"source":"obs"},{"datetime":"06:00:00","datetimeEpoch":1572876000,"temp":6.6,"feelslike":6.6,"humidity":87.29,"dew":4.6,"precip":0.0,"precipprob":null,"snow":0.0,"snowdepth":0.0,"preciptype":null,"windgust":null,"windspeed":3.2,"winddir":67.0,"pressure":1023.5,"visibility":13.0,"cloudcover":100.0,"solarradiation":null,"solarenergy":null,"uvindex":null,"conditions":"type_41","icon":"cloudy","stations":["72793024233","KSEA","KBFI","72793524234","72793494248","KRNT"],"source":"obs"},{"datetime":"07:00:00","datetimeEpoch":1572879600,"temp":5.9,"feelslike":4.4,"humidity":87.3,"dew":3.9,"precip":0.0,"precipprob":null,"snow":0.0,"snowdepth":0.0,"preciptype":null,"windgust":null,"windspeed":7.1,"winddir":120.0,"pressure":1023.5,"visibility":13.7,"cloudcover":85.4,"solarradiation":6.0,"solarenergy":0.0,"uvindex":0.0,"conditions":"type_42","icon":"partly-cloudy-day","stations":["72793024233","KSEA","E8046","KBFI","72793524234","72793494248","KRNT"],"source":"obs"},{"datetime":"08:00:00","datetimeEpoch":1572883200,"temp":6.0,"feelslike":4.4,"humidity":86.51,"dew":3.9,"precip":0.0,"precipprob":null,"snow":0.0,"snowdepth":0.0,"preciptype":null,"windgust":null,"windspeed":7.6,"winddir":133.0,"pressure":1023.9,"visibility":13.0,"cloudcover":98.3,"solarradiation":24.0,"solarenergy":0.1,"uvindex":0.0,"conditions":"type_41","icon":"cloudy","stations":["72793024233","KSEA","KBFI","72793524234","72793494248","F0821","KRNT"],"source":"obs"},{"datetime":"09:00:00","datetimeEpoch":1572886800,"temp":6.5,"feelslike":5.0,"humidity":85.69,"dew":4.2,"precip":0.0,"precipprob":null,"snow":0.0,"snowdepth":0.0,"preciptype":null,"windgust":null,"windspeed":7.5,"winddir":144.0,"pressure":1024.0,"visibility":14.3,"cloudcover":98.3,"solarradiation":71.0,"solarenergy":0.3,"uvindex":1.0,"conditions":"type_41","icon":"cloudy","stations":["72793024233","KSEA","KBFI","72793524234","72793494248","F0821","KRNT"],"source":"obs"},{"datetime":"10:00:00","datetimeEpoch":1572890400,"temp":8.3,"feelslike":8.3,"humidity":80.02,"dew":5.0,"precip":0.0,"precipprob":null,"snow":0.0,"snowdepth":0.0,"preciptype":null,"windgust":null,"windspeed":0.8,"winddir":342.0,"pressure":1024.0,"visibility":15.6,"cloudcover":100.0,"solarradiation":148.0,"solarenergy":0.5,"uvindex":1.0,"conditions":"type_41","icon":"cloudy","stations":["72793024233","KSEA","KBFI","72793524234","72793494248","F0821","KRNT"],"source":"obs"},{"datetime":"11:00:00","datetimeEpoch":1572894000,"temp":11.1,"feelslike":11.1,"humidity":75.36,"dew":6.9,"precip":0.0,"precipprob":null,"snow":0.0,"snowdepth":0.0,"preciptype":null,"windgust":null,"windspeed":2.8,"winddir":6.0,"pressure":1024.0,"visibility":16.0,"cloudcover":91.4,"solarradiation":152.0,"solarenergy":0.5,"uvindex":2.0,"conditions":"type_41","icon":"cloudy","stations":["72793024233","KSEA","KBFI","72793524234","72793494248","F0821","KRNT"],"source":"obs"},{"datetime":"12:00:00","datetimeEpoch":1572897600,"temp":12.3,"feelslike":12.3,"humidity":67.15,"dew":6.4,"precip":0.0,"precipprob":null,"snow":0.0,"snowdepth":0.0,"preciptype":null,"windgust":null,"windspeed":8.9,"winddir":46.0,"pressure":1023.8,"visibility":16.0,"cloudcover":88.2,"solarradiation":215.0,"solarenergy":0.8,"uvindex":2.0,"conditions":"type_42","icon":"partly-cloudy-day","stations":["72793024233","KSEA","KBFI","72793524234","72793494248","F0821","KRNT"],"source":"obs"},{"datetime":"13:00:00","datetimeEpoch":1572901200,"temp":13.3,"feelslike":13.3,"humidity":62.54,"dew":6.3,"precip":0.0,"precipprob":null,"snow":0.0,"snowdepth":0.0,"preciptype":null,"windgust":null,"windspeed":9.4,"winddir":360.0,"pressure":1023.2,"visibility":16.0,"cloudcover":79.1,"solarradiation":214.0,"solarenergy":0.8,"uvindex":2.0,"conditions":"type_42","icon":"partly-cloudy-day","stations":["KSEA","KBFI","72793524234","72793494248","F0821","KRNT"],"source":"obs"},{"datetime":"14:00:00","datetimeEpoch":1572904800,"temp":13.4,"feelslike":13.4,"humidity":63.72,"dew":6.6,"precip":0.0,"precipprob":null,"snow":0.0,"snowdepth":0.0,"preciptype":null,"windgust":null,"windspeed":7.5,"winddir":1.0,"pressure":1023.2,"visibility":16.0,"cloudcover":84.0,"solarradiation":155.0,"solarenergy":0.6,"uvindex":2.0,"conditions":"type_42","icon":"partly-cloudy-day","stations":["72793024233","KSEA","KBFI","72793524234","72793494248","F0821","KRNT"],"source":"obs"},{"datetime":"15:00:00","datetimeEpoch":1572908400,"temp":13.4,"feelslike":13.4,"humidity":64.09,"dew":6.7,"precip":0.0,"precipprob":null,"snow":0.0,"snowdepth":0.0,"preciptype":null,"windgust":null,"windspeed":9.8,"winddir":2.0,"pressure":1022.9,"visibility":16.0,"cloudcover":40.1,"solarradiation":157.0,"solarenergy":0.6,"uvindex":2.0,"conditions":"type_42","icon":"partly-cloudy-day","stations":["72793024233","KSEA","KBFI","72793524234","72793494248","F0821","KRNT"],"source":"obs"},{"datetime":"16:00:00","datetimeEpoch":1572912000,"temp":12.9,"feelslike":12.9,"humidity":65.84,"dew":6.6,"precip":0.0,"precipprob":null,"snow":0.0,"snowdepth":0.0,"preciptype":null,"windgust":null,"windspeed":11.0,"winddir":338.0,"pressure":1022.9,"visibility":16.0,"cloudcover":8.7,"solarradiation":98.0,"solarenergy":0.4,"uvindex":1.0,"conditions":"type_43","icon":"clear-day","stations":["72793024233","KSEA","KBFI","72793524234","72793494248","F0821","KRNT"],"source":"obs"},{"datetime":"17:00:00","datetimeEpoch":1572915600,"temp":11.5,"feelslike":11.5,"humidity":71.76,"dew":6.6,"precip":0.0,"precipprob":null,"snow":0.0,"snowdepth":0.0,"preciptype":null,"windgust":null,"windspeed":10.4,"winddir":337.0,"pressure":1022.9,"visibility":16.0,"cloudcover":37.1,"solarradiation":19.0,"solarenergy":0.1,"uvindex":0.0,"conditions":"type_42","icon":"partly-cloudy-night","stations":["72793024233","KSEA","KBFI","72793524234","72793494248","F0821","KRNT"],"source":"obs"},{"datetime":"18:00:00","datetimeEpoch":1572919200,"temp":10.5,"feelslike":10.5,"humidity":77.14,"dew":6.6,"precip":0.0,"precipprob":null,"snow":0.0,"snowdepth":0.0,"preciptype":null,"windgust":null,"windspeed":9.4,"winddir":360.0,"pressure":1022.9,"visibility":16.0,"cloudcover":5.7,"solarradiation":null,"solarenergy":null,"uvindex":null,"conditions":"type_43","icon":"clear-night","stations":["72793024233","KSEA","KBFI","72793524234","72793494248","KRNT"],"source":"obs"},{"datetime":"19:00:00","datetimeEpoch":1572922800,"temp":9.8,"feelslike":9.8,"humidity":78.14,"dew":6.2,"precip":0.0,"precipprob":null,"snow":0.0,"snowdepth":0.0,"preciptype":null,"windgust":null,"windspeed":4.7,"winddir":357.0,"pressure":1022.8,"visibility":16.0,"cloudcover":4.2,"solarradiation":null,"solarenergy":null,"uvindex":null,"conditions":"type_43","icon":"clear-night","stations":["72793024233","KSEA","KBFI","72793524234","72793494248","KRNT"],"source":"obs"},{"datetime":"20:00:00","datetimeEpoch":1572926400,"temp":9.1,"feelslike":9.1,"humidity":81.24,"dew":6.1,"precip":0.0,"precipprob":null,"snow":0.0,"snowdepth":0.0,"preciptype":null,"windgust":null,"windspeed":3.4,"winddir":360.0,"pressure":1022.9,"visibility":16.0,"cloudcover":4.2,"solarradiation":null,"solarenergy":null,"uvindex":null,"conditions":"type_43","icon":"clear-night","stations":["72793024233","KSEA","KBFI","72793524234","72793494248","KRNT"],"source":"obs"},{"datetime":"21:00:00","datetimeEpoch":1572930000,"temp":8.8,"feelslike":8.8,"humidity":83.6,"dew":6.2,"precip":0.0,"precipprob":null,"snow":0.0,"snowdepth":0.0,"preciptype":null,"windgust":null,"windspeed":4.4,"winddir":356.0,"pressure":1023.0,"visibility":15.7,"cloudcover":0.0,"solarradiation":null,"solarenergy":null,"uvindex":null,"conditions":"type_43","icon":"clear-night","stations":["72793024233","KSEA","KBFI","72793524234","72793494248","KRNT"],"source":"obs"},{"datetime":"22:00:00","datetimeEpoch":1572933600,"temp":8.5,"feelslike":8.5,"humidity":84.96,"dew":6.2,"precip":0.0,"precipprob":null,"snow":0.0,"snowdepth":0.0,"preciptype":null,"windgust":null,"windspeed":3.2,"winddir":4.0,"pressure":1023.3,"visibility":15.2,"cloudcover":0.0,"solarradiation":null,"solarenergy":null,"uvindex":null,"conditions":"type_43","icon":"clear-night","stations":["72793024233","KSEA","KBFI","72793524234","72793494248","KRNT"],"source":"obs"},{"datetime":"23:00:00","datetimeEpoch":1572937200,"temp":7.0,"feelslike":7.0,"humidity":88.85,"dew":5.3,"precip":0.0,"precipprob":null,"snow":0.0,"snowdepth":0.0,"preciptype":null,"windgust":null,"windspeed":1.7,"winddir":3.0,"pressure":1023.4,"visibility":13.3,"cloudcover":0.0,"solarradiation":null,"solarenergy":null,"uvindex":null,"conditions":"type_43","icon":"clear-night","stations":["72793024233","KSEA","KBFI","72793524234","72793494248","KRNT"],"source":"obs"}]}],"stations":{"F4154":{"distance":17440.0,"latitude":47.756,"longitude":-122.263,"useCount":0,"id":"F4154","name":"FW4154 Kenmore WA US","quality":0,"contribution":0.0},"72793024233":{"distance":18063.0,"latitude":47.444,"longitude":-122.314,"useCount":0,"id":"72793024233","name":"SEATTLE TACOMA AIRPORT, WA US","quality":100,"contribution":0.0},"KSEA":{"distance":17555.0,"latitude":47.45,"longitude":-122.3,"useCount":0,"id":"KSEA","name":"KSEA","quality":100,"contribution":0.0},"KBFI":{"distance":8819.0,"latitude":47.53,"longitude":-122.3,"useCount":0,"id":"KBFI","name":"KBFI","quality":100,"contribution":0.0},"E8046":{"distance":5899.0,"latitude":47.582,"longitude":-122.402,"useCount":0,"id":"E8046","name":"EW8046 Seattle WA US","quality":0,"contribution":0.0},"72793524234":{"distance":8766.0,"latitude":47.53,"longitude":-122.301,"useCount":0,"id":"72793524234","name":"SEATTLE BOEING FIELD, WA US","quality":100,"contribution":0.0},"72793494248":{"distance":15385.0,"latitude":47.493,"longitude":-122.214,"useCount":0,"id":"72793494248","name":"RENTON MUNICIPAL AIRPORT, WA US","quality":100,"contribution":0.0},"F0821":{"distance":1495.0,"latitude":47.612,"longitude":-122.314,"useCount":0,"id":"F0821","name":"FW0821 Seattle WA US","quality":0,"contribution":0.0},"KRNT":{"distance":14515.0,"latitude":47.5,"longitude":-122.22,"useCount":0,"id":"KRNT","name":"KRNT","quality":100,"contribution":0.0}}}